antinature/__init__.py
antinature/utils.py
antinature/core/__init__.py
antinature/core/basis.py
antinature/core/correlation.py
antinature/core/hamiltonian.py
antinature/core/integral_engine.py
antinature/core/molecular_data.py
antinature/core/scf.py
antinature/qiskit_integration/__init__.py
antinature/qiskit_integration/adapter.py
antinature/qiskit_integration/ansatze.py
antinature/qiskit_integration/antimatter_solver.py
antinature/qiskit_integration/circuits.py
antinature/qiskit_integration/systems.py
antinature/qiskit_integration/vqe_solver.py
antinature/specialized/__init__.py
antinature/specialized/annihilation.py
antinature/specialized/positronium.py
antinature/specialized/relativistic.py
antinature/specialized/visualization.py
antinature-0.1.2.dist-info/licenses/LICENSE
antinature-0.1.2.dist-info/METADATA
antinature-0.1.2.dist-info/WHEEL
antinature-0.1.2.dist-info/top_level.txt
antinature-0.1.2.dist-info/RECORD
