Metadata-Version: 2.4
Name: antinature
Version: 0.1.2
Summary: Quantum chemistry package for antimatter simulations
Home-page: https://github.com/mk0dz/antinature
Author: Mukul Kumar
Author-email: Mukul Kumar <Mukulpal108@hotmail.com>
License: MIT
Project-URL: Homepage, https://github.com/mk0dz/antinature
Project-URL: Bug Tracker, https://github.com/mk0dz/antinature/issues
Project-URL: Documentation, https://github.com/mk0dz/antinature
Classifier: Programming Language :: Python :: 3
Classifier: Programming Language :: Python :: 3.8
Classifier: Programming Language :: Python :: 3.9
Classifier: Programming Language :: Python :: 3.10
Classifier: Programming Language :: Python :: 3.11
Classifier: Programming Language :: Python :: 3.12
Classifier: Programming Language :: Python :: 3.13
Classifier: Operating System :: OS Independent
Classifier: Intended Audience :: Science/Research
Classifier: Topic :: Scientific/Engineering :: Chemistry
Classifier: Topic :: Scientific/Engineering :: Physics
Classifier: Development Status :: 4 - Beta
Requires-Python: >=3.8,<3.14
License-File: LICENSE
Requires-Dist: numpy<3.0.0,>=1.20.0
Requires-Dist: scipy<3.0.0,>=1.5.2
Requires-Dist: matplotlib<4.0.0,>=3.4.0
Requires-Dist: typing-extensions<5.0.0,>=4.0.0
Provides-Extra: qiskit
Requires-Dist: qiskit==1.4.2; extra == "qiskit"
Requires-Dist: qiskit-algorithms>=0.3.0; extra == "qiskit"
Requires-Dist: qiskit-aer>=0.17.0; extra == "qiskit"
Provides-Extra: dev
Requires-Dist: pytest<9.0.0,>=7.0.0; extra == "dev"
Requires-Dist: pytest-cov<6.0.0,>=4.0.0; extra == "dev"
Requires-Dist: black<25.0.0,>=23.0.0; extra == "dev"
Requires-Dist: isort<7.0.0,>=5.12.0; extra == "dev"
Provides-Extra: all
Requires-Dist: qiskit==1.4.2; extra == "all"
Requires-Dist: qiskit-algorithms>=0.3.0; extra == "all"
Requires-Dist: qiskit-aer>=0.17.0; extra == "all"
Requires-Dist: pytest<9.0.0,>=7.0.0; extra == "all"
Requires-Dist: pytest-cov<6.0.0,>=4.0.0; extra == "all"
Requires-Dist: black<25.0.0,>=23.0.0; extra == "all"
Requires-Dist: isort<7.0.0,>=5.12.0; extra == "all"
Dynamic: author
Dynamic: home-page
Dynamic: license-file
Dynamic: requires-python
